rcloadenv/__init__.py
rcloadenv-0.1.0.dist-info/DESCRIPTION.rst
rcloadenv-0.1.0.dist-info/METADATA
rcloadenv-0.1.0.dist-info/RECORD
rcloadenv-0.1.0.dist-info/WHEEL
rcloadenv-0.1.0.dist-info/entry_points.txt
rcloadenv-0.1.0.dist-info/metadata.json
rcloadenv-0.1.0.dist-info/top_level.txt
